[
    {
        "category_code": "category_code", 
        "category_description": "category_description", 
        "url": "url"
    }, 
    {
        "category_code": "HUMR", 
        "category_description": "Human rights", 
        "url": "http://200.38.62.10/boletin_ombudsman/boletin2/indexx.php"
    }, 
    {
        "category_code": "WOMR", 
        "category_description": "Women's rights", 
        "url": "http://200.38.62.10/mujeres/doc_basicos.html"
    }, 
    {
        "category_code": "FEXP", 
        "category_description": "Free expression and media freedom", 
        "url": "http://216.240.136.6:8000/frecuencialibre.mp3.m3u"
    }, 
    {
        "category_code": "POLT", 
        "category_description": "Political transformation", 
        "url": "http://alternativa-chiapas.blogspot.com"
    }, 
    {
        "category_code": "FEXP", 
        "category_description": "Free expression and media freedom", 
        "url": "http://amorporjuarez.com"
    }, 
    {
        "category_code": "FEXP", 
        "category_description": "Free expression and media freedom", 
        "url": "http://andreslajous.blogs.com"
    }, 
    {
        "category_code": "FREL", 
        "category_description": "Foreign relations and military", 
        "url": "http://anonimosmexico.socialgo.com"
    }, 
    {
        "category_code": "FEXP", 
        "category_description": "Free expression and media freedom", 
        "url": "http://astillero.tv"
    }, 
    {
        "category_code": "HOST", 
        "category_description": "Web hosting sites and portals", 
        "url": "http://base.espora.org/tiki-index.php"
    }, 
    {
        "category_code": "HUMR", 
        "category_description": "Human rights", 
        "url": "http://centroprodh.org.mx/agua/index.htm"
    }, 
    {
        "category_code": "HUMR", 
        "category_description": "Human rights", 
        "url": "http://centroprodh.org.mx/casos/index_casos.htm"
    }, 
    {
        "category_code": "HUMR", 
        "category_description": "Human rights", 
        "url": "http://centroprodh.org.mx/casos/oaxaca_maestros/Principal.htm"
    }, 
    {
        "category_code": "HUMR", 
        "category_description": "Human rights", 
        "url": "http://centroprodh.org.mx/de_fondho/index_defondo.htm"
    }, 
    {
        "category_code": "HUMR", 
        "category_description": "Human rights", 
        "url": "http://centroprodh.org.mx/Focus/index_focus.htm"
    }, 
    {
        "category_code": "HUMR", 
        "category_description": "Human rights", 
        "url": "http://centroprodh.org.mx/index1.htm"
    }, 
    {
        "category_code": "HUMR", 
        "category_description": "Human rights", 
        "url": "http://centroprodh.org.mx/Sala%20de%20prensa/index_prensa.htm"
    }, 
    {
        "category_code": "FEXP", 
        "category_description": "Free expression and media freedom", 
        "url": "http://chiapas.indymedia.org"
    }, 
    {
        "category_code": "FEXP", 
        "category_description": "Free expression and media freedom", 
        "url": "http://chiapatuit.net"
    }, 
    {
        "category_code": "FEXP", 
        "category_description": "Free expression and media freedom", 
        "url": "http://circulodeestudioscoapa.blogspot.com"
    }, 
    {
        "category_code": "FEXP", 
        "category_description": "Free expression and media freedom", 
        "url": "http://citivox.com"
    }, 
    {
        "category_code": "POLT", 
        "category_description": "Political transformation", 
        "url": "http://elecciones-2011.org.mx"
    }, 
    {
        "category_code": "FEXP", 
        "category_description": "Free expression and media freedom", 
        "url": "http://eluniversalgrafico.com.mx"
    }, 
    {
        "category_code": "HUMR", 
        "category_description": "Human rights", 
        "url": "http://espora.org/comitecerezo/"
    }, 
    {
        "category_code": "HUMR", 
        "category_description": "Human rights", 
        "url": "http://espora.org/comitecerezo/amenazas.php3"
    }, 
    {
        "category_code": "FEXP", 
        "category_description": "Free expression and media freedom", 
        "url": "http://espora.org/lazos_punkz/"
    }, 
    {
        "category_code": "FEXP", 
        "category_description": "Free expression and media freedom", 
        "url": "http://espora.org/revueltas/"
    }, 
    {
        "category_code": "HUMR", 
        "category_description": "Human rights", 
        "url": "http://espora.org/vientodelibertad/"
    }, 
    {
        "category_code": "FEXP", 
        "category_description": "Free expression and media freedom", 
        "url": "http://fundar.org.mx"
    }, 
    {
        "category_code": "FEXP", 
        "category_description": "Free expression and media freedom", 
        "url": "http://imc-yucatan.espora.org"
    }, 
    {
        "category_code": "FEXP", 
        "category_description": "Free expression and media freedom", 
        "url": "http://internetnecesario.org"
    }, 
    {
        "category_code": "POLT", 
        "category_description": "Political transformation", 
        "url": "http://jpsoax.blogia.com"
    }, 
    {
        "category_code": "FEXP", 
        "category_description": "Free expression and media freedom", 
        "url": "http://juarez.heroreports.org"
    }, 
    {
        "category_code": "FREL", 
        "category_description": "Foreign relations and military", 
        "url": "http://juarezenlasombra.blogspot.com"
    }, 
    {
        "category_code": "FEXP", 
        "category_description": "Free expression and media freedom", 
        "url": "http://maldeojotv.net/spip.php?breve21&var_mode=calcul"
    }, 
    {
        "category_code": "FEXP", 
        "category_description": "Free expression and media freedom", 
        "url": "http://mexico.indymedia.org"
    }, 
    {
        "category_code": "FEXP", 
        "category_description": "Free expression and media freedom", 
        "url": "http://mexico.indymedia.org/agua"
    }, 
    {
        "category_code": "FEXP", 
        "category_description": "Free expression and media freedom", 
        "url": "http://mexico.indymedia.org/indypapel"
    }, 
    {
        "category_code": "FEXP", 
        "category_description": "Free expression and media freedom", 
        "url": "http://mexico.indymedia.org/podcast"
    }, 
    {
        "category_code": "FEXP", 
        "category_description": "Free expression and media freedom", 
        "url": "http://mexico.indymedia.org/radio"
    }, 
    {
        "category_code": "FEXP", 
        "category_description": "Free expression and media freedom", 
        "url": "http://mexico.indymedia.org/tiki-download_file.php?fileId=300"
    }, 
    {
        "category_code": "FEXP", 
        "category_description": "Free expression and media freedom", 
        "url": "http://mexico.indymedia.org/tiki-download_file.php?fileId=360"
    }, 
    {
        "category_code": "FEXP", 
        "category_description": "Free expression and media freedom", 
        "url": "http://mexico.indymedia.org/tiki-index.php?page=Atenco"
    }, 
    {
        "category_code": "FEXP", 
        "category_description": "Free expression and media freedom", 
        "url": "http://mexico.indymedia.org/tiki-index.php?page=BradWill"
    }, 
    {
        "category_code": "FEXP", 
        "category_description": "Free expression and media freedom", 
        "url": "http://mexico.indymedia.org/tiki-index.php?page=EdoMex"
    }, 
    {
        "category_code": "FEXP", 
        "category_description": "Free expression and media freedom", 
        "url": "http://mexico.indymedia.org/tiki-index.php?page=LaOtraGrafika"
    }, 
    {
        "category_code": "FEXP", 
        "category_description": "Free expression and media freedom", 
        "url": "http://mexico.indymedia.org/tiki-index.php?page=MultimediaOaxaca"
    }, 
    {
        "category_code": "FEXP", 
        "category_description": "Free expression and media freedom", 
        "url": "http://mexico.indymedia.org/tiki-index.php?page=Oaxaca"
    }, 
    {
        "category_code": "FEXP", 
        "category_description": "Free expression and media freedom", 
        "url": "http://mexico.indymedia.org/tiki-index.php?page=OtraDifusion"
    }, 
    {
        "category_code": "FEXP", 
        "category_description": "Free expression and media freedom", 
        "url": "http://mexico.indymedia.org/tiki-index.php?page=PeriodicoAutonomia"
    }, 
    {
        "category_code": "FEXP", 
        "category_description": "Free expression and media freedom", 
        "url": "http://mexico.indymedia.org/tiki-index.php?page=PFP"
    }, 
    {
        "category_code": "FEXP", 
        "category_description": "Free expression and media freedom", 
        "url": "http://mexico.indymedia.org/tiki-index.php?page=PresosAmnistia"
    }, 
    {
        "category_code": "FEXP", 
        "category_description": "Free expression and media freedom", 
        "url": "http://mexico.indymedia.org/tiki-index.php?page=PresosPoliticos"
    }, 
    {
        "category_code": "FEXP", 
        "category_description": "Free expression and media freedom", 
        "url": "http://mexico.indymedia.org/tiki-index.php?page=RepresionOaxaca"
    }, 
    {
        "category_code": "FEXP", 
        "category_description": "Free expression and media freedom", 
        "url": "http://mexico.indymedia.org/tiki-index.php?page=SistemaCarcelario"
    }, 
    {
        "category_code": "FEXP", 
        "category_description": "Free expression and media freedom", 
        "url": "http://mexico.indymedia.org/tiki-list_file_gallery.php?galleryId=47"
    }, 
    {
        "category_code": "FEXP", 
        "category_description": "Free expression and media freedom", 
        "url": "http://mexico.indymedia.org/tiki-list_file_gallery.php?galleryId=48"
    }, 
    {
        "category_code": "FEXP", 
        "category_description": "Free expression and media freedom", 
        "url": "http://mexico.indymedia.org/tiki-read_article.php?articleId=245"
    }, 
    {
        "category_code": "FEXP", 
        "category_description": "Free expression and media freedom", 
        "url": "http://mexico.indymedia.org/video"
    }, 
    {
        "category_code": "FREL", 
        "category_description": "Foreign relations and military", 
        "url": "http://mexicoendescomposicion.blogspot.com"
    }, 
    {
        "category_code": "FEXP", 
        "category_description": "Free expression and media freedom", 
        "url": "http://music.napster.com/artist-music/tracks/12390707/?artist_id=12390707"
    }, 
    {
        "category_code": "FEXP", 
        "category_description": "Free expression and media freedom", 
        "url": "http://noticias-oax.com.mx"
    }, 
    {
        "category_code": "FEXP", 
        "category_description": "Free expression and media freedom", 
        "url": "http://nuestromexicobizarro.blogspot.com"
    }, 
    {
        "category_code": "FEXP", 
        "category_description": "Free expression and media freedom", 
        "url": "http://oaxacalibre.org/oaxlibre/index.php"
    }, 
    {
        "category_code": "FEXP", 
        "category_description": "Free expression and media freedom", 
        "url": "http://opendata.mx"
    }, 
    {
        "category_code": "FEXP", 
        "category_description": "Free expression and media freedom", 
        "url": "http://orelha.radiolivre.org:8000/zapote.ogg.m3u"
    }, 
    {
        "category_code": "FEXP", 
        "category_description": "Free expression and media freedom", 
        "url": "http://portal.radiobemba.org/streaming"
    }, 
    {
        "category_code": "WOMR", 
        "category_description": "Women's rights", 
        "url": "http://publicidadoficial.com.mx"
    }, 
    {
        "category_code": "FEXP", 
        "category_description": "Free expression and media freedom", 
        "url": "http://radio.indymedia.org:8000/appo.mp3.m3u"
    }, 
    {
        "category_code": "FEXP", 
        "category_description": "Free expression and media freedom", 
        "url": "http://radio.indymedia.org:8000/planton.mp3.m3u"
    }, 
    {
        "category_code": "FEXP", 
        "category_description": "Free expression and media freedom", 
        "url": "http://revolucionesmx.blogspot.com"
    }, 
    {
        "category_code": "HUMR", 
        "category_description": "Human rights", 
        "url": "http://sipaz.wordpress.com"
    }, 
    {
        "category_code": "POLT", 
        "category_description": "Political transformation", 
        "url": "http://socialismo.blogsome.com"
    }, 
    {
        "category_code": "FEXP", 
        "category_description": "Free expression and media freedom", 
        "url": "http://tijuana.indymedia.org"
    }, 
    {
        "category_code": "HUMR", 
        "category_description": "Human rights", 
        "url": "http://users.telenet.be/limeddh/"
    }, 
    {
        "category_code": "FEXP", 
        "category_description": "Free expression and media freedom", 
        "url": "http://video.indymedia.org/en/2006/11/555.shtml"
    }, 
    {
        "category_code": "FEXP", 
        "category_description": "Free expression and media freedom", 
        "url": "http://video.indymedia.org/en/2006/11/560.shtml"
    }, 
    {
        "category_code": "FEXP", 
        "category_description": "Free expression and media freedom", 
        "url": "http://videos.eluniversal.com.mx/videos.html"
    }, 
    {
        "category_code": "FEXP", 
        "category_description": "Free expression and media freedom", 
        "url": "http://www.8columnas.com.mx"
    }, 
    {
        "category_code": "FEXP", 
        "category_description": "Free expression and media freedom", 
        "url": "http://www.aca-novenet.com.mx"
    }, 
    {
        "category_code": "POLT", 
        "category_description": "Political transformation", 
        "url": "http://www.alternativa.org.mx"
    }, 
    {
        "category_code": "POLT", 
        "category_description": "Political transformation", 
        "url": "http://www.alternativa.org.mx/default.asp?id=386"
    }, 
    {
        "category_code": "POLT", 
        "category_description": "Political transformation", 
        "url": "http://www.alternativa.org.mx/default.asp?id=600"
    }, 
    {
        "category_code": "POLT", 
        "category_description": "Political transformation", 
        "url": "http://www.alternativa.org.mx/default.asp?proceso=saladeprensa"
    }, 
    {
        "category_code": "POLT", 
        "category_description": "Political transformation", 
        "url": "http://www.alternativabc.org.mx"
    }, 
    {
        "category_code": "POLT", 
        "category_description": "Political transformation", 
        "url": "http://www.alternativadf.org.mx"
    }, 
    {
        "category_code": "HUMR", 
        "category_description": "Human rights", 
        "url": "http://www.amar-ac.org"
    }, 
    {
        "category_code": "HUMR", 
        "category_description": "Human rights", 
        "url": "http://www.amdh.com.mx"
    }, 
    {
        "category_code": "WOMR", 
        "category_description": "Women's rights", 
        "url": "http://www.amdh.com.mx/mujeres/"
    }, 
    {
        "category_code": "HUMR", 
        "category_description": "Human rights", 
        "url": "http://www.amdh.com.mx/ombudsweb/"
    }, 
    {
        "category_code": "FEXP", 
        "category_description": "Free expression and media freedom", 
        "url": "http://www.amlo.org.mx"
    }, 
    {
        "category_code": "WOMR", 
        "category_description": "Women's rights", 
        "url": "http://www.animalpolitico.com"
    }, 
    {
        "category_code": "MINR", 
        "category_description": "Minority rights and ethnic content", 
        "url": "http://www.badeso.org/principal.htm"
    }, 
    {
        "category_code": "FEXP", 
        "category_description": "Free expression and media freedom", 
        "url": "http://www.blogdelnarco.com"
    }, 
    {
        "category_code": "FEXP", 
        "category_description": "Free expression and media freedom", 
        "url": "http://www.cambiodemichoacan.com.mx"
    }, 
    {
        "category_code": "FEXP", 
        "category_description": "Free expression and media freedom", 
        "url": "http://www.cambioenlinea.com"
    }, 
    {
        "category_code": "HUMR", 
        "category_description": "Human rights", 
        "url": "http://www.casasaludgenesis.org.mx"
    }, 
    {
        "category_code": "HUMR", 
        "category_description": "Human rights", 
        "url": "http://www.cdh-chiapas.org.mx"
    }, 
    {
        "category_code": "HUMR", 
        "category_description": "Human rights", 
        "url": "http://www.cdh-chiapas.org.mx/index.php?option=com_content&task=category&sectionid=2&id=22&Itemid=28"
    }, 
    {
        "category_code": "MINR", 
        "category_description": "Minority rights and ethnic content", 
        "url": "http://www.cdi.gob.mx"
    }, 
    {
        "category_code": "FEXP", 
        "category_description": "Free expression and media freedom", 
        "url": "http://www.cdi.gob.mx/audio_cdi/mira/mira_mito_mazorca.ram"
    }, 
    {
        "category_code": "FEXP", 
        "category_description": "Free expression and media freedom", 
        "url": "http://www.cdi.gob.mx/audio_cdi/voces/voces_zezv_totopos.ram"
    }, 
    {
        "category_code": "MINR", 
        "category_description": "Minority rights and ethnic content", 
        "url": "http://www.cdi.gob.mx/derechos/vigencia_libro/vigencia_derechos_indigenas_septiembre_2007.pdf"
    }, 
    {
        "category_code": "FEXP", 
        "category_description": "Free expression and media freedom", 
        "url": "http://www.cdi.gob.mx/index.php?id_seccion=1558"
    }, 
    {
        "category_code": "MINR", 
        "category_description": "Minority rights and ethnic content", 
        "url": "http://www.cdi.gob.mx/informe2005/CDI_informe_2005.pdf"
    }, 
    {
        "category_code": "MINR", 
        "category_description": "Minority rights and ethnic content", 
        "url": "http://www.cdi.gob.mx/informe2006/CDI_informe_2006.pdf"
    }, 
    {
        "category_code": "HUMR", 
        "category_description": "Human rights", 
        "url": "http://www.ciepac.org/accionesurgentes/accionesnacionales.php"
    }, 
    {
        "category_code": "HUMR", 
        "category_description": "Human rights", 
        "url": "http://www.ciepac.org/boletines/ultimo.php"
    }, 
    {
        "category_code": "HUMR", 
        "category_description": "Human rights", 
        "url": "http://www.ciepac.org/campanas/transgenicos.php"
    }, 
    {
        "category_code": "HUMR", 
        "category_description": "Human rights", 
        "url": "http://www.ciepac.org/foros/ultimos.php"
    }, 
    {
        "category_code": "HUMR", 
        "category_description": "Human rights", 
        "url": "http://www.ciepac.org/index.php"
    }, 
    {
        "category_code": "HUMR", 
        "category_description": "Human rights", 
        "url": "http://www.ciepac.org/mapas/militares/"
    }, 
    {
        "category_code": "FEXP", 
        "category_description": "Free expression and media freedom", 
        "url": "http://www.ciepac.org/neoliberal/esp/index.html"
    }, 
    {
        "category_code": "FEXP", 
        "category_description": "Free expression and media freedom", 
        "url": "http://www.ciepac.org/neoliberal/index.html"
    }, 
    {
        "category_code": "HUMR", 
        "category_description": "Human rights", 
        "url": "http://www.ciepac.org/temas/ezln/caracoles.php#none"
    }, 
    {
        "category_code": "HUMR", 
        "category_description": "Human rights", 
        "url": "http://www.ciepac.org/temas/quesla-appo.pdf"
    }, 
    {
        "category_code": "POLT", 
        "category_description": "Political transformation", 
        "url": "http://www.colectivocasa.org"
    }, 
    {
        "category_code": "HUMR", 
        "category_description": "Human rights", 
        "url": "http://www.conganas.org.mx"
    }, 
    {
        "category_code": "HAL", 
        "category_description": "History, arts and literature", 
        "url": "http://www.contraelvientofilms.com"
    }, 
    {
        "category_code": "POLT", 
        "category_description": "Political transformation", 
        "url": "http://www.convergencia.org.mx"
    }, 
    {
        "category_code": "POLT", 
        "category_description": "Political transformation", 
        "url": "http://www.convergencia.org.mx/index.php?option=com_content&task=blogcategory&id=97&Itemid=226"
    }, 
    {
        "category_code": "POLT", 
        "category_description": "Political transformation", 
        "url": "http://www.convergencia.org.mx/index.php?option=com_content&task=view&id=257&Itemid=219"
    }, 
    {
        "category_code": "FEXP", 
        "category_description": "Free expression and media freedom", 
        "url": "http://www.correo-gto.com.mx"
    }, 
    {
        "category_code": "FEXP", 
        "category_description": "Free expression and media freedom", 
        "url": "http://www.cronica.com.mx/refresh.php"
    }, 
    {
        "category_code": "FEXP", 
        "category_description": "Free expression and media freedom", 
        "url": "http://www.cuarto-poder.com.mx"
    }, 
    {
        "category_code": "HUMR", 
        "category_description": "Human rights", 
        "url": "http://www.derechoshumanos.org.mx"
    }, 
    {
        "category_code": "HUMR", 
        "category_description": "Human rights", 
        "url": "http://www.derechoshumanos.org.mx/extras/download/CAT-C-MEX-CO-4%20adopted.pdf"
    }, 
    {
        "category_code": "HUMR", 
        "category_description": "Human rights", 
        "url": "http://www.derechoshumanos.org.mx/modules.php?name=Acciones_Urgentes"
    }, 
    {
        "category_code": "HUMR", 
        "category_description": "Human rights", 
        "url": "http://www.derechoshumanos.org.mx/modules.php?name=Content&pa=showpage&pid=104"
    }, 
    {
        "category_code": "HUMR", 
        "category_description": "Human rights", 
        "url": "http://www.derechoshumanos.org.mx/modules.php?name=Content&pa=showpage&pid=30"
    }, 
    {
        "category_code": "HUMR", 
        "category_description": "Human rights", 
        "url": "http://www.derechoshumanos.org.mx/modules.php?name=Publications"
    }, 
    {
        "category_code": "HUMR", 
        "category_description": "Human rights", 
        "url": "http://www.derechoshumanosenmexico.org"
    }, 
    {
        "category_code": "HUMR", 
        "category_description": "Human rights", 
        "url": "http://www.derechoshumanosenmexico.org/estadisticas2.htm"
    }, 
    {
        "category_code": "HUMR", 
        "category_description": "Human rights", 
        "url": "http://www.derechoshumanosenmexico.org/informemilitares07.htm"
    }, 
    {
        "category_code": "HUMR", 
        "category_description": "Human rights", 
        "url": "http://www.derechoshumanosenmexico.org/informes/INFORME%20DE%20MIGRACION.htm"
    }, 
    {
        "category_code": "HUMR", 
        "category_description": "Human rights", 
        "url": "http://www.derechoshumanosenmexico.org/Secciones/Medio%20Ambiente.htm"
    }, 
    {
        "category_code": "HUMR", 
        "category_description": "Human rights", 
        "url": "http://www.derechoshumanosenmexico.org/videoproducciones07.htm"
    }, 
    {
        "category_code": "FEXP", 
        "category_description": "Free expression and media freedom", 
        "url": "http://www.despertardelsur.com"
    }, 
    {
        "category_code": "FEXP", 
        "category_description": "Free expression and media freedom", 
        "url": "http://www.diagonalperiodico.net/recherche.php3?recherche=mexico"
    }, 
    {
        "category_code": "FEXP", 
        "category_description": "Free expression and media freedom", 
        "url": "http://www.diario.com.mx"
    }, 
    {
        "category_code": "FEXP", 
        "category_description": "Free expression and media freedom", 
        "url": "http://www.diario17.com"
    }, 
    {
        "category_code": "FEXP", 
        "category_description": "Free expression and media freedom", 
        "url": "http://www.diario21.com.mx"
    }, 
    {
        "category_code": "FEXP", 
        "category_description": "Free expression and media freedom", 
        "url": "http://www.diarioamanecer.com.mx"
    }, 
    {
        "category_code": "FEXP", 
        "category_description": "Free expression and media freedom", 
        "url": "http://www.diariodecolima.com"
    }, 
    {
        "category_code": "FEXP", 
        "category_description": "Free expression and media freedom", 
        "url": "http://www.diariodemexico.com.mx"
    }, 
    {
        "category_code": "FEXP", 
        "category_description": "Free expression and media freedom", 
        "url": "http://www.diariodemexicousa.com"
    }, 
    {
        "category_code": "FEXP", 
        "category_description": "Free expression and media freedom", 
        "url": "http://www.diariodemorelos.com"
    }, 
    {
        "category_code": "FEXP", 
        "category_description": "Free expression and media freedom", 
        "url": "http://www.diariomonitor.com.mx"
    }, 
    {
        "category_code": "MINR", 
        "category_description": "Minority rights and ethnic content", 
        "url": "http://www.e-indigenas.gob.mx"
    }, 
    {
        "category_code": "FEXP", 
        "category_description": "Free expression and media freedom", 
        "url": "http://www.el-heraldo-bajio.com.mx"
    }, 
    {
        "category_code": "FEXP", 
        "category_description": "Free expression and media freedom", 
        "url": "http://www.el-mexicano.com.mx"
    }, 
    {
        "category_code": "FEXP", 
        "category_description": "Free expression and media freedom", 
        "url": "http://www.elboomeran.com/blog/175/agresiones-cotidianas-blog-de-sanjuana-martinez/"
    }, 
    {
        "category_code": "FEXP", 
        "category_description": "Free expression and media freedom", 
        "url": "http://www.eldiariodechihuahua.com.mx"
    }, 
    {
        "category_code": "FEXP", 
        "category_description": "Free expression and media freedom", 
        "url": "http://www.eldiariodecoahuila.com.mx"
    }, 
    {
        "category_code": "FEXP", 
        "category_description": "Free expression and media freedom", 
        "url": "http://www.elnuevosiglo.com.mx"
    }, 
    {
        "category_code": "FEXP", 
        "category_description": "Free expression and media freedom", 
        "url": "http://www.elorbe.com.mx"
    }, 
    {
        "category_code": "FEXP", 
        "category_description": "Free expression and media freedom", 
        "url": "http://www.elporvenir.com.mx"
    }, 
    {
        "category_code": "FEXP", 
        "category_description": "Free expression and media freedom", 
        "url": "http://www.elregio.com/site/index.php"
    }, 
    {
        "category_code": "FEXP", 
        "category_description": "Free expression and media freedom", 
        "url": "http://www.elsiglodedurango.com.mx"
    }, 
    {
        "category_code": "FEXP", 
        "category_description": "Free expression and media freedom", 
        "url": "http://www.elsur.com.mx"
    }, 
    {
        "category_code": "FEXP", 
        "category_description": "Free expression and media freedom", 
        "url": "http://www.eluniversal.com.mx/noticias.html"
    }, 
    {
        "category_code": "FEXP", 
        "category_description": "Free expression and media freedom", 
        "url": "http://www.enfoqueinformativo.com"
    }, 
    {
        "category_code": "FEXP", 
        "category_description": "Free expression and media freedom", 
        "url": "http://www.espora.org/jar/"
    }, 
    {
        "category_code": "FEXP", 
        "category_description": "Free expression and media freedom", 
        "url": "http://www.espora.org/klat/"
    }, 
    {
        "category_code": "FEXP", 
        "category_description": "Free expression and media freedom", 
        "url": "http://www.excelsiorinternet.com"
    }, 
    {
        "category_code": "ENV", 
        "category_description": "Environment", 
        "url": "http://www.florafaunaycultura.org"
    }, 
    {
        "category_code": "MINR", 
        "category_description": "Minority rights and ethnic content", 
        "url": "http://www.fondopaz.org"
    }, 
    {
        "category_code": "HUMR", 
        "category_description": "Human rights", 
        "url": "http://www.frayba.org.mx/acciones_urgentes.php"
    }, 
    {
        "category_code": "HUMR", 
        "category_description": "Human rights", 
        "url": "http://www.frayba.org.mx/denuncias.php"
    }, 
    {
        "category_code": "HUMR", 
        "category_description": "Human rights", 
        "url": "http://www.frayba.org.mx/index.php"
    }, 
    {
        "category_code": "HUMR", 
        "category_description": "Human rights", 
        "url": "http://www.frayba.org.mx/informes.php"
    }, 
    {
        "category_code": "FEXP", 
        "category_description": "Free expression and media freedom", 
        "url": "http://www.frontera.info"
    }, 
    {
        "category_code": "POLT", 
        "category_description": "Political transformation", 
        "url": "http://www.fuerzaciudadana.org.mx"
    }, 
    {
        "category_code": "POLT", 
        "category_description": "Political transformation", 
        "url": "http://www.fuerzaciudadana.org.mx/forojuvenil/FORO%20JUVENIL%202005-20061.pdf"
    }, 
    {
        "category_code": "POLT", 
        "category_description": "Political transformation", 
        "url": "http://www.fuerzaciudadana.org.mx/haciendo/propuesta.html"
    }, 
    {
        "category_code": "POLT", 
        "category_description": "Political transformation", 
        "url": "http://www.fuerzaciudadana.org.mx/noticias/index.html"
    }, 
    {
        "category_code": "POLT", 
        "category_description": "Political transformation", 
        "url": "http://www.fuerzaciudadana.org.mx/universitarios/index.html"
    }, 
    {
        "category_code": "MILX", 
        "category_description": "Militants, extremists and separatists", 
        "url": "http://www.fzln.org.mx"
    }, 
    {
        "category_code": "MILX", 
        "category_description": "Militants, extremists and separatists", 
        "url": "http://www.fzln.org.mx/grupos-guerrilleros-en-mexico"
    }, 
    {
        "category_code": "FREL", 
        "category_description": "Foreign relations and military", 
        "url": "http://www.impactolegislativo.org.mx/sitio/"
    }, 
    {
        "category_code": "FEXP", 
        "category_description": "Free expression and media freedom", 
        "url": "http://www.imparcialenlinea.com"
    }, 
    {
        "category_code": "FEXP", 
        "category_description": "Free expression and media freedom", 
        "url": "http://www.informador.com.mx/informador/"
    }, 
    {
        "category_code": "FEXP", 
        "category_description": "Free expression and media freedom", 
        "url": "http://www.intoleranciadiario.com"
    }, 
    {
        "category_code": "FEXP", 
        "category_description": "Free expression and media freedom", 
        "url": "http://www.johnackerman.blogspot.com"
    }, 
    {
        "category_code": "FEXP", 
        "category_description": "Free expression and media freedom", 
        "url": "http://www.jornada.unam.mx"
    }, 
    {
        "category_code": "POLT", 
        "category_description": "Political transformation", 
        "url": "http://www.jps.org.mx"
    }, 
    {
        "category_code": "POLT", 
        "category_description": "Political transformation", 
        "url": "http://www.jps.org.mx/documentos/index.html"
    }, 
    {
        "category_code": "POLT", 
        "category_description": "Political transformation", 
        "url": "http://www.jps.org.mx/documentos/llamamiento.html"
    }, 
    {
        "category_code": "FEXP", 
        "category_description": "Free expression and media freedom", 
        "url": "http://www.kehuelga.org/stream.m3u"
    }, 
    {
        "category_code": "FEXP", 
        "category_description": "Free expression and media freedom", 
        "url": "http://www.lacrisis.com.mx"
    }, 
    {
        "category_code": "FEXP", 
        "category_description": "Free expression and media freedom", 
        "url": "http://www.lacronica.com"
    }, 
    {
        "category_code": "FEXP", 
        "category_description": "Free expression and media freedom", 
        "url": "http://www.lajornadamorelos.com"
    }, 
    {
        "category_code": "HUMR", 
        "category_description": "Human rights", 
        "url": "http://www.laneta.apc.org/cidhmor/"
    }, 
    {
        "category_code": "HUMR", 
        "category_description": "Human rights", 
        "url": "http://www.laneta.apc.org/cidhmor/agenda-mujeres.html"
    }, 
    {
        "category_code": "HUMR", 
        "category_description": "Human rights", 
        "url": "http://www.laneta.apc.org/cidhmor/noticias.html"
    }, 
    {
        "category_code": "HUMR", 
        "category_description": "Human rights", 
        "url": "http://www.laneta.apc.org/sinfronteras/"
    }, 
    {
        "category_code": "FEXP", 
        "category_description": "Free expression and media freedom", 
        "url": "http://www.lasnoticiasmexico.com"
    }, 
    {
        "category_code": "FEXP", 
        "category_description": "Free expression and media freedom", 
        "url": "http://www.launion.com.mx"
    }, 
    {
        "category_code": "HUMR", 
        "category_description": "Human rights", 
        "url": "http://www.metamorfosis.org.mx"
    }, 
    {
        "category_code": "FEXP", 
        "category_description": "Free expression and media freedom", 
        "url": "http://www.mexicodenuncia.org"
    }, 
    {
        "category_code": "FEXP", 
        "category_description": "Free expression and media freedom", 
        "url": "http://www.mexicodenuncia.org/alertas.html"
    }, 
    {
        "category_code": "FEXP", 
        "category_description": "Free expression and media freedom", 
        "url": "http://www.mexicodenuncia.org/amenazas.html"
    }, 
    {
        "category_code": "FEXP", 
        "category_description": "Free expression and media freedom", 
        "url": "http://www.mexicodenuncia.org/apoyo.html"
    }, 
    {
        "category_code": "FEXP", 
        "category_description": "Free expression and media freedom", 
        "url": "http://www.mexicodenuncia.org/extorsion.html"
    }, 
    {
        "category_code": "FEXP", 
        "category_description": "Free expression and media freedom", 
        "url": "http://www.mexicodenuncia.org/hermandad.html"
    }, 
    {
        "category_code": "FEXP", 
        "category_description": "Free expression and media freedom", 
        "url": "http://www.mexicodenuncia.org/index1.htm"
    }, 
    {
        "category_code": "FEXP", 
        "category_description": "Free expression and media freedom", 
        "url": "http://www.mexicodenuncia.org/informes.html"
    }, 
    {
        "category_code": "FEXP", 
        "category_description": "Free expression and media freedom", 
        "url": "http://www.mexicodenuncia.org/pfp.html"
    }, 
    {
        "category_code": "FEXP", 
        "category_description": "Free expression and media freedom", 
        "url": "http://www.mexicodenuncia.org/prensa.html"
    }, 
    {
        "category_code": "FEXP", 
        "category_description": "Free expression and media freedom", 
        "url": "http://www.mexicodenuncia.org/registros.html"
    }, 
    {
        "category_code": "FEXP", 
        "category_description": "Free expression and media freedom", 
        "url": "http://www.mexicodenuncia.org/victimas.html"
    }, 
    {
        "category_code": "HUMR", 
        "category_description": "Human rights", 
        "url": "http://www.mexicounido.org.mx"
    }, 
    {
        "category_code": "HUMR", 
        "category_description": "Human rights", 
        "url": "http://www.mexicounido.org.mx/investigacionmegatendencias.html"
    }, 
    {
        "category_code": "HUMR", 
        "category_description": "Human rights", 
        "url": "http://www.mexicounido.org.mx/investigacionpaginas.html"
    }, 
    {
        "category_code": "FEXP", 
        "category_description": "Free expression and media freedom", 
        "url": "http://www.milenio.com/index.php?c=mexico/"
    }, 
    {
        "category_code": "WOMR", 
        "category_description": "Women's rights", 
        "url": "http://www.mujeres.amnistia.org.mx/section.php?name=ciudadjuarez"
    }, 
    {
        "category_code": "WOMR", 
        "category_description": "Women's rights", 
        "url": "http://www.mujeres.amnistia.org.mx/section.php?name=home"
    }, 
    {
        "category_code": "WOMR", 
        "category_description": "Women's rights", 
        "url": "http://www.mujeres.amnistia.org.mx/section.php?name=informes_23112004"
    }, 
    {
        "category_code": "POLT", 
        "category_description": "Political transformation", 
        "url": "http://www.mujeresdejuarez.org"
    }, 
    {
        "category_code": "FEXP", 
        "category_description": "Free expression and media freedom", 
        "url": "http://www.natlaw.com/mexico/diario/diario.htm"
    }, 
    {
        "category_code": "FEXP", 
        "category_description": "Free expression and media freedom", 
        "url": "http://www.nortedeciudadjuarez.com"
    }, 
    {
        "category_code": "POLT", 
        "category_description": "Political transformation", 
        "url": "http://www.nueva-alianza.org.mx"
    }, 
    {
        "category_code": "POLT", 
        "category_description": "Political transformation", 
        "url": "http://www.nueva-alianza.org.mx/index.asp?action=content.main&cID=51"
    }, 
    {
        "category_code": "FEXP", 
        "category_description": "Free expression and media freedom", 
        "url": "http://www.oem.com.mx/elsoldelcentro/default.aspx"
    }, 
    {
        "category_code": "FEXP", 
        "category_description": "Free expression and media freedom", 
        "url": "http://www.oem.com.mx/elsoldemexico/default.aspx"
    }, 
    {
        "category_code": "FEXP", 
        "category_description": "Free expression and media freedom", 
        "url": "http://www.oem.com.mx/elsoldeparral/default.aspx"
    }, 
    {
        "category_code": "FEXP", 
        "category_description": "Free expression and media freedom", 
        "url": "http://www.oem.com.mx/elsoldetijuana/default.aspx"
    }, 
    {
        "category_code": "FEXP", 
        "category_description": "Free expression and media freedom", 
        "url": "http://www.oem.com.mx/elsudcaliforniano/default.aspx"
    }, 
    {
        "category_code": "FEXP", 
        "category_description": "Free expression and media freedom", 
        "url": "http://www.oem.com.mx/laprensa/default.aspx"
    }, 
    {
        "category_code": "FEXP", 
        "category_description": "Free expression and media freedom", 
        "url": "http://www.oem.com.mx/lavozdelafrontera/default.aspx"
    }, 
    {
        "category_code": "FEXP", 
        "category_description": "Free expression and media freedom", 
        "url": "http://www.opinion.com.mx"
    }, 
    {
        "category_code": "HUMR", 
        "category_description": "Human rights", 
        "url": "http://www.paginasprodigy.com/jramond/index.html"
    }, 
    {
        "category_code": "FEXP", 
        "category_description": "Free expression and media freedom", 
        "url": "http://www.palabra.com"
    }, 
    {
        "category_code": "POLT", 
        "category_description": "Political transformation", 
        "url": "http://www.pan.org.mx"
    }, 
    {
        "category_code": "POLT", 
        "category_description": "Political transformation", 
        "url": "http://www.pan.org.mx/?P=documentos"
    }, 
    {
        "category_code": "POLT", 
        "category_description": "Political transformation", 
        "url": "http://www.pan.org.mx/?P=podcast"
    }, 
    {
        "category_code": "POLT", 
        "category_description": "Political transformation", 
        "url": "http://www.pan.org.mx/?P=revista_nacion"
    }, 
    {
        "category_code": "POLT", 
        "category_description": "Political transformation", 
        "url": "http://www.pan.org.mx/nacion/2284.pdf.zip"
    }, 
    {
        "category_code": "POLT", 
        "category_description": "Political transformation", 
        "url": "http://www.pan.org.mx/nacion/2301.pdf.zip"
    }, 
    {
        "category_code": "FEXP", 
        "category_description": "Free expression and media freedom", 
        "url": "http://www.periodicoavance.com"
    }, 
    {
        "category_code": "POLT", 
        "category_description": "Political transformation", 
        "url": "http://www.ppsdemexico.org"
    }, 
    {
        "category_code": "POLT", 
        "category_description": "Political transformation", 
        "url": "http://www.ppsdemexico.org/documentos/index.html"
    }, 
    {
        "category_code": "POLT", 
        "category_description": "Political transformation", 
        "url": "http://www.ppsdemexico.org/teoriaypractica/index.html"
    }, 
    {
        "category_code": "POLT", 
        "category_description": "Political transformation", 
        "url": "http://www.ppsm.org.mx"
    }, 
    {
        "category_code": "POLT", 
        "category_description": "Political transformation", 
        "url": "http://www.ppsm.org.mx/comunistas/index.html"
    }, 
    {
        "category_code": "POLT", 
        "category_description": "Political transformation", 
        "url": "http://www.ppsm.org.mx/rebeldia/index.html"
    }, 
    {
        "category_code": "POLT", 
        "category_description": "Political transformation", 
        "url": "http://www.prd.org.mx"
    }, 
    {
        "category_code": "POLT", 
        "category_description": "Political transformation", 
        "url": "http://www.prd.org.mx/index.php?option=com_content&task=category&sectionid=2&id=15&Itemid=29"
    }, 
    {
        "category_code": "POLT", 
        "category_description": "Political transformation", 
        "url": "http://www.pri.org.mx/LaRepublicaGeneral/conArticuloPrincipal.aspx?p=&s="
    }, 
    {
        "category_code": "POLT", 
        "category_description": "Political transformation", 
        "url": "http://www.pri.org.mx/ReconstruccionXXI/default.aspx"
    }, 
    {
        "category_code": "POLT", 
        "category_description": "Political transformation", 
        "url": "http://www.pri.org.mx/ReconstruccionXXI/Elecciones/Informe_Elecciones.pdf"
    }, 
    {
        "category_code": "POLT", 
        "category_description": "Political transformation", 
        "url": "http://www.pri.org.mx/ReconstruccionXXI/NuestroPartido/DocumentosBasicos/documentosbasicos.aspx"
    }, 
    {
        "category_code": "POLT", 
        "category_description": "Political transformation", 
        "url": "http://www.pri.org.mx/ReconstruccionXXI/Publicaciones/Examen.aspx"
    }, 
    {
        "category_code": "POLT", 
        "category_description": "Political transformation", 
        "url": "http://www.pt-tamaulipas.org"
    }, 
    {
        "category_code": "POLT", 
        "category_description": "Political transformation", 
        "url": "http://www.pt-tamaulipas.org/docbasicos.pdf"
    }, 
    {
        "category_code": "POLT", 
        "category_description": "Political transformation", 
        "url": "http://www.pt.org.mx"
    }, 
    {
        "category_code": "FEXP", 
        "category_description": "Free expression and media freedom", 
        "url": "http://www.puebla.sintesisdigital.net"
    }, 
    {
        "category_code": "POLR", 
        "category_description": "Political reform", 
        "url": "http://www.pvem.org.mx/web/"
    }, 
    {
        "category_code": "POLR", 
        "category_description": "Political reform", 
        "url": "http://www.pvem.org.mx/web/index.php?option=com_content&task=section&id=4&Itemid=43"
    }, 
    {
        "category_code": "POLR", 
        "category_description": "Political reform", 
        "url": "http://www.pvem.org.mx/web/index.php?option=com_content&task=view&id=5&Itemid=6"
    }, 
    {
        "category_code": "POLR", 
        "category_description": "Political reform", 
        "url": "http://www.pvem.org.mx/web/index.php?option=com_wrapper&Itemid=87"
    }, 
    {
        "category_code": "WOMR", 
        "category_description": "Women's rights", 
        "url": "http://www.quequedeclaro.org.mx/home/"
    }, 
    {
        "category_code": "FEXP", 
        "category_description": "Free expression and media freedom", 
        "url": "http://www.radiopacheco.org"
    }, 
    {
        "category_code": "FEXP", 
        "category_description": "Free expression and media freedom", 
        "url": "http://www.radiozapatista.org"
    }, 
    {
        "category_code": "HUMR", 
        "category_description": "Human rights", 
        "url": "http://www.redtdt.org.mx/wwwf/acciones.php"
    }, 
    {
        "category_code": "HUMR", 
        "category_description": "Human rights", 
        "url": "http://www.redtdt.org.mx/wwwf/boletines.php"
    }, 
    {
        "category_code": "HUMR", 
        "category_description": "Human rights", 
        "url": "http://www.redtdt.org.mx/wwwf/index.php"
    }, 
    {
        "category_code": "HUMR", 
        "category_description": "Human rights", 
        "url": "http://www.redtdt.org.mx/wwwf/informes.php"
    }, 
    {
        "category_code": "FEXP", 
        "category_description": "Free expression and media freedom", 
        "url": "http://www.reforma.com"
    }, 
    {
        "category_code": "FEXP", 
        "category_description": "Free expression and media freedom", 
        "url": "http://www.revistarebeldia.org"
    }, 
    {
        "category_code": "FEXP", 
        "category_description": "Free expression and media freedom", 
        "url": "http://www.revistarebeldia.org/html/descargas/rebeldia_41.pdf"
    }, 
    {
        "category_code": "FEXP", 
        "category_description": "Free expression and media freedom", 
        "url": "http://www.revistarebeldia.org/html/descargas/rebeldia_42.pdf"
    }, 
    {
        "category_code": "FEXP", 
        "category_description": "Free expression and media freedom", 
        "url": "http://www.revistarebeldia.org/html/descargas/rebeldia_43.pdf"
    }, 
    {
        "category_code": "FREL", 
        "category_description": "Foreign relations and military", 
        "url": "http://www.rmalc.org.mx/documentos.htm"
    }, 
    {
        "category_code": "FREL", 
        "category_description": "Foreign relations and military", 
        "url": "http://www.rmalc.org.mx/index.shtml"
    }, 
    {
        "category_code": "FREL", 
        "category_description": "Foreign relations and military", 
        "url": "http://www.rmalc.org.mx/libros.htm"
    }, 
    {
        "category_code": "FREL", 
        "category_description": "Foreign relations and military", 
        "url": "http://www.rmalc.org.mx/prensa.htm"
    }, 
    {
        "category_code": "HUMR", 
        "category_description": "Human rights", 
        "url": "http://www.sipaz.org"
    }, 
    {
        "category_code": "HUMR", 
        "category_description": "Human rights", 
        "url": "http://www.sipaz.org/crono/procesp.htm"
    }, 
    {
        "category_code": "HUMR", 
        "category_description": "Human rights", 
        "url": "http://www.sipaz.org/documentos/docs_esp.htm"
    }, 
    {
        "category_code": "HUMR", 
        "category_description": "Human rights", 
        "url": "http://www.sipaz.org/documentos/docs_esp.htm#ACTEAL"
    }, 
    {
        "category_code": "HUMR", 
        "category_description": "Human rights", 
        "url": "http://www.sipaz.org/documentos/docs_esp.htm#DESPLA"
    }, 
    {
        "category_code": "HUMR", 
        "category_description": "Human rights", 
        "url": "http://www.sipaz.org/documentos/docs_esp.htm#MILI"
    }, 
    {
        "category_code": "HUMR", 
        "category_description": "Human rights", 
        "url": "http://www.sipaz.org/gfini_esp.htm"
    }, 
    {
        "category_code": "HUMR", 
        "category_description": "Human rights", 
        "url": "http://www.sipaz.org/gro_problem/problem_idxs.htm"
    }, 
    {
        "category_code": "HUMR", 
        "category_description": "Human rights", 
        "url": "http://www.sipaz.org/informes/inf_esp.htm"
    }, 
    {
        "category_code": "HUMR", 
        "category_description": "Human rights", 
        "url": "http://www.sipaz.org/oax_problem/docs/info_oax0710.pdf"
    }, 
    {
        "category_code": "HUMR", 
        "category_description": "Human rights", 
        "url": "http://www.sipaz.org/oax_problem/oproblem_idx.html"
    }, 
    {
        "category_code": "HUMR", 
        "category_description": "Human rights", 
        "url": "http://www.sitio.de/presospoliticos/"
    }, 
    {
        "category_code": "FEXP", 
        "category_description": "Free expression and media freedom", 
        "url": "http://www.tiempoenlinea.com.mx"
    }, 
    {
        "category_code": "FEXP", 
        "category_description": "Free expression and media freedom", 
        "url": "http://www.tribunacampeche.com"
    }, 
    {
        "category_code": "POLT", 
        "category_description": "Political transformation", 
        "url": "http://www.unidad.org.mx"
    }, 
    {
        "category_code": "POLT", 
        "category_description": "Political transformation", 
        "url": "http://www.unidad.org.mx/unidad_old"
    }, 
    {
        "category_code": "FEXP", 
        "category_description": "Free expression and media freedom", 
        "url": "http://www.unomasuno.com.mx"
    }, 
    {
        "category_code": "FEXP", 
        "category_description": "Free expression and media freedom", 
        "url": "http://www.vozdemichoacan.com.mx"
    }, 
    {
        "category_code": "FEXP", 
        "category_description": "Free expression and media freedom", 
        "url": "http://www.zocalo.com.mx"
    }, 
    {
        "category_code": "FEXP", 
        "category_description": "Free expression and media freedom", 
        "url": "https://mexicanosalgrito.wordpress.com"
    }, 
    {
        "category_code": "FEXP", 
        "category_description": "Free expression and media freedom", 
        "url": "https://sanjuancopalaoaxaca.wordpress.com"
    }, 
    {
        "category_code": "FEXP", 
        "category_description": "Free expression and media freedom", 
        "url": "https://video.indymedia.org/en/2007/04/800.shtml"
    }
]
